aihems/__init__.py
aihems_pkg-0.0.1.dist-info/METADATA
aihems_pkg-0.0.1.dist-info/WHEEL
aihems_pkg-0.0.1.dist-info/top_level.txt
aihems_pkg-0.0.1.dist-info/RECORD
