Metadata-Version: 2.1
Name: aihems-pkg
Version: 0.0.1
Summary: AIHEMS
Home-page: https://github.com/byungjin0826/ai-hems-new
Author: byungjin0826
Author-email: byungjin0826@gmail.com
License: UNKNOWN
Platform: UNKNOWN
Classifier: Programming Language :: Python :: 3
Classifier: License :: OSI Approved :: MIT License
Classifier: Operating System :: OS Independent
Requires-Python: >=3.6
